matrixg
