Metadata-Version: 1.0
Name: matrixg
Version: 5.3
Summary: Solve matrix by Gaussian and Jacoby
Home-page: UNKNOWN
Author: UNKNOWN
Author-email: shpeka4kaps4@mail.ru
License: UNKNOWN
Platform: UNKNOWN
